intelligentic/__init__.py
intelligentic/agents/__init__.py
intelligentic/agents/agent_judge.py
intelligentic/agents/agent_print.py
intelligentic/agents/ape_agent.py
intelligentic/agents/auto_generate_swarm_config.py
intelligentic/agents/consistency_agent.py
intelligentic/agents/create_agents_from_yaml.py
intelligentic/agents/exceptions.py
intelligentic/agents/flexion_agent.py
intelligentic/agents/gkp_agent.py
intelligentic/agents/i_agent.py
intelligentic/agents/openai_assistant.py
intelligentic/agents/react_agent.py
intelligentic/agents/reasoning_agents.py
intelligentic/agents/reasoning_duo.py
intelligentic/artifacts/__init__.py
intelligentic/artifacts/main_artifact.py
intelligentic/cli/__init__.py
intelligentic/cli/main.py
intelligentic/prompts/__init__.py
intelligentic/prompts/accountant_swarm_prompts.py
intelligentic/prompts/ag_prompt.py
intelligentic/prompts/aga.py
intelligentic/prompts/agent_conversation_aggregator.py
intelligentic/prompts/agent_judge_prompt.py
intelligentic/prompts/agent_orchestration_prompt.py
intelligentic/prompts/agent_prompts.py
intelligentic/prompts/agent_self_builder_prompt.py
intelligentic/prompts/agent_system_prompts.py
intelligentic/prompts/ai_research_team.py
intelligentic/prompts/aot_prompt.py
intelligentic/prompts/autobloggen.py
intelligentic/prompts/autoswarm.py
intelligentic/prompts/code_interpreter.py
intelligentic/prompts/code_spawner.py
intelligentic/prompts/collaborative_prompts.py
intelligentic/prompts/debate.py
intelligentic/prompts/documentation.py
intelligentic/prompts/education.py
intelligentic/prompts/finance_agent_prompt.py
intelligentic/prompts/finance_agent_sys_prompt.py
intelligentic/prompts/growth_agent_prompt.py
intelligentic/prompts/hiearchical_system_prompt.py
intelligentic/prompts/idea2img.py
intelligentic/prompts/legal_agent_prompt.py
intelligentic/prompts/logistics.py
intelligentic/prompts/max_loop_prompt.py
intelligentic/prompts/meta_system_prompt.py
intelligentic/prompts/moa_prompt.py
intelligentic-1.0.0.dist-info/entry_points.txt
intelligentic-1.0.0.dist-info/LICENSE
intelligentic-1.0.0.dist-info/METADATA
intelligentic-1.0.0.dist-info/WHEEL
intelligentic-1.0.0.dist-info/RECORD
